zyng/__init__.py
zyng/core.py
zyng/runner.py
zyng-0.1.0.dist-info/METADATA
zyng-0.1.0.dist-info/WHEEL
zyng-0.1.0.dist-info/top_level.txt
zyng-0.1.0.dist-info/RECORD
