Metadata-Version: 2.4
Name: zyng
Version: 0.1.0
Summary: A tiny timeline-first language for LLM workflows and logs.
Author-email: Yo Kobayashi <yaw.kobayashi@proton.me>
License-Expression: MIT
Project-URL: Homepage, https://github.com/YawKobayashi/zyng
Requires-Python: >=3.10
